setup.py
google_forms/__init__.py
google_forms/google_forms.py
google_forms.egg-info/PKG-INFO
google_forms.egg-info/SOURCES.txt
google_forms.egg-info/dependency_links.txt
google_forms.egg-info/not-zip-safe
google_forms.egg-info/top_level.txt