Metadata-Version: 1.0
Name: google-forms
Version: 0.2
Summary: Flask web proxy for Google forms
Home-page: http://github.com/logicalicy/google_forms
Author: Logicalicy
Author-email: logicalicy.com@gmail.com
License: MIT
Platform: UNKNOWN
